setup.py
prob_dist_udacity/Binomialdistribution.py
prob_dist_udacity/Gaussiandistribution.py
prob_dist_udacity/Generaldistribution.py
prob_dist_udacity/__init__.py
prob_dist_udacity.egg-info/PKG-INFO
prob_dist_udacity.egg-info/SOURCES.txt
prob_dist_udacity.egg-info/dependency_links.txt
prob_dist_udacity.egg-info/not-zip-safe
prob_dist_udacity.egg-info/top_level.txt