Metadata-Version: 1.0
Name: prob-dist-udacity
Version: 1.1
Summary: Gaussian and Binomial distributions
Home-page: UNKNOWN
Author: Sunil Kumar Vuppala
Author-email: sunilkumar.vuppala01@gmail.com
License: UNKNOWN
Platform: UNKNOWN
